emarketlib/__init__.py
emarketlib/assume.py
emarketlib/base_market.py
emarketlib/example_configs.py
emarketlib/example_eu.py
emarketlib/grid_utils.py
emarketlib/market_objects.py
emarketlib/utils.py
emarketlib-0.0.1.dist-info/METADATA
emarketlib-0.0.1.dist-info/WHEEL
emarketlib-0.0.1.dist-info/top_level.txt
emarketlib-0.0.1.dist-info/RECORD
