Metadata-Version: 2.1
Name: emarketlib
Version: 0.0.1
Summary: Energy market toolbox
Author-email: Florian Maurer <maurer@fh-aachen.de>
License: AGPL-3.0-or-later
Project-URL: homepage, https://github.com/assume-framework/emarketlib
Project-URL: repository, https://github.com/assume-framework/emarketlib
Keywords: agent based simulation,energy market,market simulation,simulation
Classifier: Development Status :: 4 - Beta
Classifier: Intended Audience :: Developers
Classifier: Operating System :: OS Independent
Classifier: Framework :: AsyncIO
Classifier: Topic :: Scientific/Engineering
Classifier: Topic :: Software Development :: Libraries :: Python Modules
Classifier: Programming Language :: Python :: 3 :: Only
Classifier: Programming Language :: Python :: 3.10
Classifier: Programming Language :: Python :: 3.11
Classifier: Programming Language :: Python :: 3.12
Classifier: Programming Language :: Python :: 3.13
Requires-Python: >=3.10
Requires-Dist: argcomplete >=3.1.4
Requires-Dist: mango-agents >=1.2
Requires-Dist: numpy >=1.26.4
Requires-Dist: python-dateutil >=2.8.2
Requires-Dist: pandas >=2.0.0
Requires-Dist: pyyaml >=6.0.2
Provides-Extra: test
Requires-Dist: ruff >=0.4.9 ; extra == 'test'
Requires-Dist: mypy >=1.1.1 ; extra == 'test'
Requires-Dist: matplotlib >=3.7.2 ; extra == 'test'
Requires-Dist: pytest >=7.2.2 ; extra == 'test'
Requires-Dist: pytest-cov >=4.1.0 ; extra == 'test'
Requires-Dist: pytest-asyncio >=0.21.1 ; extra == 'test'
